img2pdf/__init__.py
img2pdf/main.py
img2pdf_plus-1.1.3.dist-info/LICENSE
img2pdf_plus-1.1.3.dist-info/METADATA
img2pdf_plus-1.1.3.dist-info/WHEEL
img2pdf_plus-1.1.3.dist-info/entry_points.txt
img2pdf_plus-1.1.3.dist-info/top_level.txt
img2pdf_plus-1.1.3.dist-info/RECORD
