Metadata-Version: 2.1
Name: img2pdf-plus
Version: 1.1.3
Summary: Merge images into one pdf file including useful optiıns via command line.
Home-page: https://github.com/Elagoht/img2pdf
Author: Furkan Baytekin (Elagoht)
Author-email: furkanbaytekin@gmail.com
Project-URL: Bug Tracker, https://github.com/Elagoht/img2pdf/issues
Classifier: Programming Language :: Python :: 3
Classifier: License :: OSI Approved :: MIT License
Classifier: Operating System :: OS Independent
Requires-Python: >=3.6
License-File: LICENSE
Requires-Dist: fonttools (>=4.38.0)
Requires-Dist: fpdf2 (>=2.6.0)
Requires-Dist: Pillow (>=9.3.0)
Requires-Dist: python-magic (>=0.4.27) ; platform_system != "Windows"
Requires-Dist: python-magic-bin (==0.4.14) ; platform_system == "Windows"
